{"items":[
{"key":"초코서당-상담 및 필자 안내 글모음#0007","cat":"C16"},
{"key":"초코서당-상담 및 필자 안내 글모음#0008","cat":"C16"},
{"key":"초코서당-상담 및 필자 안내 글모음#0009","cat":"C16"},
{"key":"초코서당-수강안내 글모음#0000","cat":"C16"},
{"key":"초코서당-수강안내 글모음#0001","cat":"C16"},
{"key":"초코서당-수강안내 글모음#0002","cat":"C16"},
{"key":"초코서당-신년운세 모음 글모음#0000","cat":"C10"},
{"key":"초코서당-신년운세 모음 글모음#0001","cat":"C10"},
{"key":"초코서당-신년운세 모음 글모음#0002","cat":"C10"},
{"key":"초코서당-신년운세 모음 글모음#0003","cat":"C10"},
{"key":"초코서당-신년운세 모음 글모음#0004","cat":"C10"},
{"key":"초코서당-신년운세 모음 글모음#0005","cat":"C10"},
{"key":"초코서당-신년운세 모음 글모음#0006","cat":"C03"},
{"key":"초코서당-신년운세 모음 글모음#0007","cat":"C03"},
{"key":"초코서당-신년운세 모음 글모음#0008","cat":"C10"},
{"key":"초코서당-신년운세 모음 글모음#0009","cat":"C10"},
{"key":"초코서당-신살 글모음#0000","cat":"C06"},
{"key":"초코서당-신살 글모음#0001","cat":"C03"},
{"key":"초코서당-십성, 육친 글모음#0000","cat":"C04"},
{"key":"초코서당-십성, 육친 글모음#0001","cat":"C04"},
{"key":"초코서당-음양, 오행 글모음#0000","cat":"C01"},
{"key":"초코서당-음양, 오행 글모음#0001","cat":"C01"},
{"key":"초코서당-음양, 오행 글모음#0002","cat":"C01"},
{"key":"초코서당-음양, 오행 글모음#0003","cat":"C01"},
{"key":"초코서당-음양, 오행 글모음#0004","cat":"C01"},
{"key":"초코서당-음양, 오행 글모음#0005","cat":"C01"},
{"key":"초코서당-음양, 오행 글모음#0006","cat":"C01"},
{"key":"초코서당-음양, 오행 글모음#0007","cat":"C13"},
{"key":"초코서당-음양, 오행 글모음#0008","cat":"C01"},
{"key":"초코서당-일상이야기 글모음#0000","cat":"C16"},
{"key":"초코서당-일상이야기 글모음#0001","cat":"C16"},
{"key":"초코서당-일상이야기 글모음#0002","cat":"C16"},
{"key":"초코서당-일상이야기 글모음#0003","cat":"C16"},
{"key":"초코서당-일주론 글모음#0000","cat":"C05"},
{"key":"초코서당-일주론 글모음#0001","cat":"C05"},
{"key":"초코서당-천간, 지지 글모음#0000","cat":"C02"},
{"key":"초코서당-천간, 지지 글모음#0001","cat":"C02"},
{"key":"초코서당-천간, 지지 글모음#0002","cat":"C02"},
{"key":"초코서당-천간, 지지 글모음#0003","cat":"C02"},
{"key":"초코서당-천간, 지지 글모음#0004","cat":"C02"},
{"key":"초코서당-천간, 지지 글모음#0005","cat":"C02"},
{"key":"초코서당-천간, 지지 글모음#0006","cat":"C02"},
{"key":"초코서당-천간, 지지 글모음#0007","cat":"C02"},
{"key":"초코서당-천간, 지지 글모음#0008","cat":"C02"},
{"key":"초코서당-천간, 지지 글모음#0009","cat":"C02"},
{"key":"초코서당-천간, 지지 글모음#0010","cat":"C02"},
{"key":"초코서당-천간, 지지 글모음#0011","cat":"C02"},
{"key":"초코서당-천간, 지지 글모음#0012","cat":"C02"},
{"key":"초코서당-천간, 지지 글모음#0013","cat":"C02"},
{"key":"초코서당-천간, 지지 글모음#0014","cat":"C02"},
{"key":"초코서당-천간, 지지 글모음#0015","cat":"C02"},
{"key":"초코서당-천간, 지지 글모음#0016","cat":"C02"},
{"key":"초코서당-합, 충, 형 글모음#0000","cat":"C03"},
{"key":"초코서당-합, 충, 형 글모음#0001","cat":"C03"},
{"key":"택일기타사용설명 게시판 글모음#0000","cat":"C16"},
{"key":"택일기타사용설명 게시판 글모음#0001","cat":"C15"},
{"key":"파이브시즌스 글모음#0000","cat":"C16"},
{"key":"파이브시즌스 글모음#0001","cat":"C16"},
{"key":"파이브시즌스 글모음#0002","cat":"C16"},
{"key":"파이브시즌스 글모음#0003","cat":"C16"},
{"key":"파이브시즌스 글모음#0004","cat":"C16"},
{"key":"파이브시즌스 글모음#0005","cat":"C16"},
{"key":"파이브시즌스 글모음#0006","cat":"C16"},
{"key":"파이브시즌스 글모음#0007","cat":"C16"},
{"key":"파이브시즌스 글모음#0008","cat":"C16"},
{"key":"파이브시즌스 글모음#0009","cat":"C16"},
{"key":"파이브시즌스 글모음#0010","cat":"C16"},
{"key":"파이브시즌스 글모음#0011","cat":"C16"},
{"key":"파이브시즌스 글모음#0012","cat":"C16"},
{"key":"파이브시즌스 글모음#0013","cat":"C16"},
{"key":"파이브시즌스 글모음#0014","cat":"C16"},
{"key":"파이브시즌스 글모음#0015","cat":"C16"},
{"key":"파이브시즌스 글모음#0016","cat":"C16"},
{"key":"파이브시즌스 글모음#0017","cat":"C16"},
{"key":"파이브시즌스 글모음#0018","cat":"C16"},
{"key":"파이브시즌스 글모음#0019","cat":"C16"},
{"key":"파이브시즌스 글모음#0020","cat":"C16"},
{"key":"파이브시즌스 글모음#0021","cat":"C16"},
{"key":"파이브시즌스 글모음#0022","cat":"C16"},
{"key":"파이브시즌스 글모음#0023","cat":"C16"},
{"key":"파이브시즌스 글모음#0024","cat":"C16"},
{"key":"파이브시즌스 글모음#0025","cat":"C16"},
{"key":"파이브시즌스 글모음#0026","cat":"C16"},
{"key":"파이브시즌스 글모음#0027","cat":"C16"},
{"key":"파이브시즌스 글모음#0028","cat":"C16"},
{"key":"파이브시즌스 글모음#0029","cat":"C16"},
{"key":"파이브시즌스 글모음#0030","cat":"C16"},
{"key":"파이브시즌스 글모음#0031","cat":"C16"},
{"key":"파이브시즌스 글모음#0032","cat":"C16"},
{"key":"파이브시즌스 글모음#0033","cat":"C16"}
]}
